MeCab.py
_MeCab.cp36-win32.pyd
mecab_python_windows-0.996.3.data/data/lib/site-packages/libmecab.dll
mecab_python_windows-0.996.3.dist-info/DESCRIPTION.rst
mecab_python_windows-0.996.3.dist-info/METADATA
mecab_python_windows-0.996.3.dist-info/RECORD
mecab_python_windows-0.996.3.dist-info/WHEEL
mecab_python_windows-0.996.3.dist-info/metadata.json
mecab_python_windows-0.996.3.dist-info/top_level.txt
